{
  "id": "li_ming",
  "name": "李明",
  "age": 28,
  "gender": "male",
  "visible_request": "稍微剪短，精神一些",
  "hidden_need": "想要适合职场形象的自然侧分",
  "initial_emotion": "nervous",
  "initial_hairstyle_file": "res://data/hairstyles/li_ming_initial.json",
  "target_hairstyle_id": "short_neat_style",
  "target_hairstyle_file": "res://data/hairstyles/short_neat_style.json",
  "dialogue_file": "res://data/dialogues/li_ming_dialogue.json",
  "scoring_profile_file": "res://data/scoring/scoring_profile_li_ming.json",
  "feedback_file": "res://data/feedback/feedback_li_ming.json",
  "visual_profile": {
    "shirt_color": "0.4,0.35,0.3",
    "skin_tone": "0.95,0.85,0.7",
    "hair_color": "0.15,0.1,0.1",
    "pants_color": "0.25,0.2,0.15"
  }
}
