{
  "id": "li_ming_dialogue",
  "intro": "你好，我想理个发。",
  "summary": "好的，我明白了，大概就是剪短一些，保持职场形象。",
  "rounds": [
    {
      "id": "greeting",
      "speaker": "customer",
      "text": "你好，请问现在可以理发吗？",
      "options": [
        {
          "text": "当然可以，请到这边坐。（微笑）",
          "next_round": "ask_need",
          "effects": {
            "trust": 1,
            "understanding": 1,
            "emotion": "relaxed"
          }
        },
        {
          "text": "可以，你先坐下吧。",
          "next_round": "ask_need",
          "effects": {
            "trust": 0,
            "understanding": 0,
            "emotion": "neutral"
          }
        },
        {
          "text": "等一下，我先收拾一下。",
          "next_round": "ask_need",
          "effects": {
            "trust": -1,
            "understanding": 0,
            "emotion": "worried"
          }
        }
      ]
    },
    {
      "id": "ask_need",
      "speaker": "customer",
      "text": "我想把头发稍微剪短一些，看起来精神点。",
      "options": [
        {
          "text": "好的，你是想要比较清爽干练的感觉吧？",
          "next_round": "detail",
          "effects": {
            "trust": 1,
            "understanding": 2,
            "emotion": "trusting"
          }
        },
        {
          "text": "明白，想修短一些。工作场合用吗？",
          "next_round": "detail",
          "effects": {
            "trust": 1,
            "understanding": 1,
            "emotion": "relaxed"
          }
        },
        {
          "text": "嗯，剪短是吧？行，交给我。",
          "next_round": "detail",
          "effects": {
            "trust": 0,
            "understanding": 0,
            "emotion": "neutral"
          }
        }
      ]
    },
    {
      "id": "detail",
      "speaker": "customer",
      "text": "嗯，我平时要上班，想看起来专业一些。不过不要太短，稍微有型就好。",
      "options": [
        {
          "text": "那我觉得自然侧分的风格很适合你，上班不会太夸张，又显得精神。",
          "next_round": "hidden_need",
          "effects": {
            "trust": 2,
            "understanding": 3,
            "revealed_hidden_need": true,
            "emotion": "satisfied"
          }
        },
        {
          "text": "那我帮你整体剪短，上面留一点长度，可以打理成型。",
          "next_round": "confirm",
          "effects": {
            "trust": 1,
            "understanding": 2,
            "emotion": "trusting"
          }
        },
        {
          "text": "两边推短，上面剪短一些，怎么样？",
          "next_round": "confirm",
          "effects": {
            "trust": 0,
            "understanding": 1,
            "emotion": "neutral"
          }
        }
      ]
    },
    {
      "id": "hidden_need",
      "speaker": "customer",
      "text": "对！我就是想要那种感觉，你说到点子上了！我之前还不太好意思说想要侧分，怕太麻烦。",
      "options": [
        {
          "text": "不麻烦，这种风格很适合你，我们开始吧。",
          "next_round": "",
          "effects": {
            "trust": 2,
            "understanding": 2,
            "emotion": "relaxed"
          }
        },
        {
          "text": "那就这样定了，保证让你满意。",
          "next_round": "",
          "effects": {
            "trust": 1,
            "understanding": 1,
            "emotion": "trusting"
          }
        }
      ]
    },
    {
      "id": "confirm",
      "speaker": "customer",
      "text": "好的，那就麻烦你了。",
      "next_round": "",
      "options": [
        {
          "text": "不客气，我们开始吧。",
          "effects": {
            "trust": 1,
            "understanding": 0,
            "emotion": "neutral"
          }
        }
      ]
    }
  ]
}
